Workbook

Sheet Assumptions
A1: VoiceBridge — Financial Model & Assumptions
A2: Sunstone Innovation Challenge 2026 | Confidential
A4: LEGEND
A5: Blue text = Hardcoded inputs (change for scenarios)
A6: Black text = Formulas / calculated
A7: Yellow bg = Key assumptions needing attention
A9: PRICING ASSUMPTIONS
A10: Personal Pro — Annual Price ($/yr) | B10: 99 | C10: Survey-validated; below $4,500 annual time-value
A11: Personal Pro — Monthly Equivalent ($/mo) | B11: =B10/12 -> 8.25 | C11: Calculated: annual / 12
A12: Team — Annual Price ($/user/yr) | B12: 49 | C12: Per user/yr — team lead deployment channel
A13: Institutional — Low ($/yr) | B13: 3000 | C13: BMAC pilot comparable institutions
A14: Institutional — High ($/yr) | B14: 8000 | C14: Large university / enterprise tier
A15: Institutional — Average ($/yr) | B15: =(B13+B14)/2 -> 5500 | C15: Calculated midpoint for projections
A16: Beta Pre-Order Price ($/yr) | B16: 49 | C16: 30.3% pre-order commitment rate from survey (n=33)
A18: UNIT ECONOMICS & COST ASSUMPTIONS
A19: AI/API Cost per User per Year ($) | B19: 6
A20: Cloud Infra Cost per User per Year ($) | B20: 15
A21: Blended COGS per User per Year ($) | B21: =B19+B20 -> 21
A22: Blended CAC — Year 1 (PLG, no paid ads) ($) | B22: 20
A23: Blended CAC — Year 2 ($) | B23: 18
A24: Blended CAC — Year 3 ($) | B24: 15
A25: Annual Churn Rate (%) | B25: 0.05
A26: Average Subscription Length (yrs) | B26: 2.5
A27: LTV — Pro (ARPU × avg life) ($) | B27: =B10*B26 -> 247.5
A28: LTV/CAC Ratio — Y1 | B28: =B27/B22 -> 12.375

Sheet Y1 Monthly Forecast
A1: a
A2: Pro tier: $99/yr billed annually → $8.25/mo MRR equivalent. Institutional revenue recognized at contract signing.
A3: Month | B3: Free Users (cumul.) | C3: New Pro Users | D3: Pro Users (cumul.) | E3: MRR ($) | F3: Institutional Revenue ($) | G3: Total Revenue ($) | H3: Monthly Expense ($) | I3: Net Income ($) | J3: Notes
A4: Apr 2026 | B4: 30 | C4: 0 | D4: 0 | E4: =D4*(Assumptions!B10/12) -> 0 | F4: 0 | G4: =E4+F4 -> 0 | H4: 2500 | I4: =G4-H4 -> -2500 | J4: Beta build, BMAC onboarding
A5: May 2026 | B5: 80 | C5: 0 | D5: 0 | E5: =D5*(Assumptions!B10/12) -> 0 | F5: 0 | G5: =E5+F5 -> 0 | H5: 2800 | I5: =G5-H5 -> -2800 | J5: Campus ambassador launch
A6: Jun 2026 | B6: 150 | C6: 5 | D6: 5 | E6: =D6*(Assumptions!B10/12) -> 41.25 | F6: 0 | G6: =E6+F6 -> 41.25 | H6: 3000 | I6: =G6-H6 -> -2958.75 | J6: Closed beta — first 5 paid
A7: Jul 2026 | B7: 250 | C7: 10 | D7: 15 | E7: =D7*(Assumptions!B10/12) -> 123.75 | F7: 0 | G7: =E7+F7 -> 123.75 | H7: 3200 | I7: =G7-H7 -> -3076.25 | J7: Beta expands
A8: Aug 2026 | B8: 400 | C8: 20 | D8: 35 | E8: =D8*(Assumptions!B10/12) -> 288.75 | F8: 0 | G8: =E8+F8 -> 288.75 | H8: 3200 | I8: =G8-H8 -> -2911.25 | J8: Usage cap conversions
A9: Sep 2026 | B9: 600 | C9: 30 | D9: 65 | E9: =D9*(Assumptions!B10/12) -> 536.25 | F9: 0 | G9: =E9+F9 -> 536.25 | H9: 3500 | I9: =G9-H9 -> -2963.75 | J9: Word-of-mouth accelerates
A10: Oct 2026 | B10: 900 | C10: 55 | D10: 120 | E10: =D10*(Assumptions!B10/12) -> 990 | F10: 0 | G10: =E10+F10 -> 990 | H10: 4500 | I10: =G10-H10 -> -3510 | J10: Product Hunt launch
A11: Nov 2026 | B11: 1200 | C11: 60 | D11: 180 | E11: =D11*(Assumptions!B10/12) -> 1485 | F11: 0 | G11: =E11+F11 -> 1485 | H11: 3800 | I11: =G11-H11 -> -2315 | J11: Post-PH conversion wave
A12: Dec 2026 | B12: 1500 | C12: 70 | D12: 250 | E12: =D12*(Assumptions!B10/12) -> 2062.5 | F12: 0 | G12: =E12+F12 -> 2062.5 | H12: 3800 | I12: =G12-H12 -> -1737.5 | J12: Holiday / semester break push
A13: Jan 2027 | B13: 1700 | C13: 40 | D13: 290 | E13: =D13*(Assumptions!B10/12) -> 2392.5 | F13: 0 | G13: =E13+F13 -> 2392.5 | H13: 3500 | I13: =G13-H13 -> -1107.5 | J13: Spring semester activation
A14: Feb 2027 | B14: 1850 | C14: 30 | D14: 320 | E14: =D14*(Assumptions!B10/12) -> 2640 | F14: 0 | G14: =E14+F14 -> 2640 | H14: 3500 | I14: =G14-H14 -> -860 | J14: BMAC pilot results published
A15: Mar 2027 | B15: 2000 | C15: 30 | D15: 350 | E15: =D15*(Assumptions!B10/12) -> 2887.5 | F15: 8000 | G15: =E15+F15 -> 10887.5 | H15: 3200 | I15: =G15-H15 -> 7687.5 | J15: 1st institutional contract signed
A16: FULL YEAR TOTAL | B16: =D15 -> 350 | C16: =SUM(C4:C15) -> 350 | D16: =D15 -> 350 | E16: =SUM(E4:E15) -> 13447.5 | F16: =SUM(F4:F15) -> 8000 | G16: =SUM(G4:G15) -> 21447.5 | H16: =SUM(H4:H15) -> 40500 | I16: =SUM(I4:I15) -> -19052.5 | J16: ARR exit rate ≈ MRR×12 = ~$34.7K

Sheet 3-Year P&L
A1: VoiceBridge — 3-Year Profit & Loss Summary
B3: Year 1 (Apr 2026–Mar 2027) | C3: Year 2 (Apr 2027–Mar 2028) | D3: Year 3 (Apr 2028–Mar 2029) | E3: 3-Year Total
A4: REVENUE
A5: Personal Pro Subscriptions | B5: 34650 | C5: 148500 | D5: 396000 | E5: =SUM(B5:D5) -> 579150
A6: Team Licenses | B6: 0 | C6: 19600 | D6: 73500 | E6: =SUM(B6:D6) -> 93100
A7: Institutional Contracts | B7: 8000 | C7: 30000 | D7: 75000 | E7: =SUM(B7:D7) -> 113000
A8: TOTAL REVENUE | B8: =SUM(B5:B7) -> 42650 | C8: =SUM(C5:C7) -> 198100 | D8: =SUM(D5:D7) -> 544500 | E8: =SUM(E5:E7) -> 785250
A9: COST OF REVENUE (COGS)
A10: AI/API + Cloud Infrastructure | B10: 6000 | C10: 18500 | D10: 46000 | E10: =SUM(B10:D10) -> 70500
A11: GROSS PROFIT | B11: =B8-B10 -> 36650 | C11: =C8-C10 -> 179600 | D11: =D8-D10 -> 498500 | E11: =E8-E10 -> 714750
A12: Gross Margin % | B12: =IFERROR(B11/B8,0) -> 0.85932005 | C12: =IFERROR(C11/C8,0) -> 0.90661282 | D12: =IFERROR(D11/D8,0) -> 0.91551882 | E12: =IFERROR(E11/E8,0) -> 0.91021968
A13: OPERATING EXPENSES
A14: AI / API | B14: 2500 | C14: 10000 | D14: 28000 | E14: =SUM(B14:D14) -> 40500
A15: Cloud / Hosting | B15: 2300 | C15: 6000 | D15: 14000 | E15: =SUM(B15:D15) -> 22300
A16: Software Tools | B16: 1200 | C16: 2500 | D16: 4000 | E16: =SUM(B16:D16) -> 7700
A17: User Research | B17: 2000 | C17: 3500 | D17: 5000 | E17: =SUM(B17:D17) -> 10500
A18: Marketing & Growth | B18: 7000 | C18: 30000 | D18: 65000 | E18: =SUM(B18:D18) -> 102000
A19: Legal / IP | B19: 4500 | C19: 8000 | D19: 15000 | E19: =SUM(B19:D19) -> 27500
A20: Contractors | B20: 20000 | C20: 58500 | D20: 121000 | E20: =SUM(B20:D20) -> 199500
A21: Founder Compensation | B21: 0 | C21: 24000 | D21: 60000 | E21: =SUM(B21:D21) -> 84000
A22: TOTAL OPERATING EXPENSES | B22: =SUM(B14:B21) -> 39500 | C22: =SUM(C14:C21) -> 142500 | D22: =SUM(D14:D21) -> 312000 | E22: =SUM(E14:E21) -> 494000
A23: OPERATING INCOME / (LOSS) | B23: =B11-B22 -> -2850 | C23: =C11-C22 -> 37100 | D23: =D11-D22 -> 186500 | E23: =E11-E22 -> 220750
A24: Operating Margin % | B24: =IFERROR(B23/B8,0) -> -0.066822978 | C24: =IFERROR(C23/C8,0) -> 0.18727915 | D24: =IFERROR(D23/D8,0) -> 0.34251607 | E24: =IFERROR(E23/E8,0) -> 0.28112066
A25: Cumulative Operating Cash | B25: =B23 -> -2850 | C25: =B25+C23 -> 34250 | D25: =C25+D23 -> 220750 | E25: =D25 -> 220750

Sheet Sensitivity Analysis
A1: VoiceBridge — Sensitivity Analysis (Year 3 Projections)
A2: All scenarios assume only one variable changes at a time vs. base case, unless otherwise stated.
A4: Scenario | B4: Change from Base | C4: Y3 Revenue Impact ($) | D4: Y3 Operating Income ($) | E4: Verdict | F4: Key Lever
A5: Base Case | B5: As projected | C5: 544500 | D5: 232500 | E5: Healthy | F5: All assumptions met
A6: Activation drops 40% | B6: 57% fewer entering funnel | C6: 310000 | D6: 65000 | E6: Profitable — slower growth | F6: Fix onboarding / first command UX
A7: W4 Retention = 20% | B7: 50% higher churn | C7: 340000 | D7: 95000 | E7: Profitable — fix retention | F7: Narrow to 3 highest-repeat workflows
A8: Institutional = +12mo | B8: Y1: 0 pilots, Y2: 2, Y3: 6 | C8: 505000 | D8: 210000 | E8: Minor impact | F8: Consumer Pro sustains independently
A9: CAC doubles ($40) | B9: Marketing spend 2× | C9: 544500 | D9: 167500 | E9: Still strong margins | F9: Delay scale spend, optimize PLG
A10: All of the above | B10: Worst realistic combined | C10: 200000 | D10: 0 | E10: Breakeven — restructure | F10: Prove W4 retention before scaling

Sheet Unit Economics
A1: VoiceBridge — Unit Economics Dashboard
A3: METRIC | B3: VALUE | C3: BASIS
A4: ARPU — Personal Pro ($/yr) | B4: =Assumptions!B10 -> 99 | C4: Survey-validated (n=33); 72.7% open to $99/yr
A5: ARPU — Team ($/user/yr) | B5: =Assumptions!B12 -> 49 | C5: Per-seat team license
A6: Cost of Service / User / Yr | B6: =Assumptions!B19 -> 6 | C6: Grok XAI + infra (sub-linear at scale)
A7: Gross Margin — Pro Tier | B7: =(Assumptions!B10-Assumptions!B19)/Assumptions!B10 -> 0.93939394 | C7: 85–93% software-typical
A8: Blended CAC — Y1 (PLG) | B8: =Assumptions!B20 -> 15 | C8: Campus ambassadors, Product Hunt, organic Reddit
A9: Average Customer Lifetime (yrs) | B9: 2.5 | C9: 2.5 yr estimate; low for students, high for accessibility users
A10: LTV — Pro (ARPU × life) | B10: =Assumptions!B10*Assumptions!B23 -> 1782 | C10: ARPU × avg subscription life
A11: LTV / CAC Ratio | B11: =Assumptions!B24/Assumptions!B20 -> 1 | C11: >3:1 SaaS benchmark; VoiceBridge target >10:1
A12: Payback Period (months) | B12: =Assumptions!B20/(Assumptions!B10/12) -> 1.8181818 | C12: Months to recover CAC from monthly revenue
A13: Break-Even Users | B13: 40 | C13: Monthly OpEx / monthly ARPU (Y1 base)
A14: Y3 SOM Penetration | B14: =4000/480000 -> 0.0083333333 | C14: 4,000 Pro users / 480K SAM

Sheet Use of Sunstone Funds
A1: VoiceBridge — Use of Sunstone $15,000 Grant
A3: Allocation Category | B3: Amount ($) | C3: % of Total | D3: Purpose
A4: Beta Infrastructure | B4: 3000 | C4: =B4/15000 -> 0.2 | D4: Supabase, PostHog, CI/CD, code signing (12 months)
A5: Beta Recruitment | B5: 2500 | C5: =B5/15000 -> 0.16666667 | D5: Tester incentives + 3 campus ambassadors
A6: UX Research | B6: 3000 | C6: =B6/15000 -> 0.2 | D6: 40 hrs usability testing — retention-critical
A7: Test Hardware | B7: 2000 | C7: =B7/15000 -> 0.13333333 | D7: Windows laptop + Android device for QA
A8: Legal / IP | B8: 2500 | C8: =B8/15000 -> 0.16666667 | D8: LLC formation, trademark, privacy policy, ToS
A9: BMAC Pilot + CSUN Conference | B9: 2000 | C9: =B9/15000 -> 0.13333333 | D9: Pilot materials + CSUN AT Conference attendance
A10: TOTAL GRANT REQUESTED | B10: =SUM(B4:B9) -> 15000 | C10: 1
